standard_names/__init__.py
standard_names/error.py
standard_names/registry.py
standard_names/standardname.py
standard_names/cmd/__init__.py
standard_names/cmd/snbuild.py
standard_names/cmd/sndump.py
standard_names/cmd/snscrape.py
standard_names/cmd/snsql.py
standard_names/cmd/snvalidate.py
standard_names/data/names-0.8.3.txt
standard_names/data/names-0.8.5.txt
standard_names/tests/__init__.py
standard_names/tests/test_io.py
standard_names/tests/test_namesregistry.py
standard_names/tests/test_standardname.py
standard_names/utilities/__init__.py
standard_names/utilities/decorators.py
standard_names/utilities/io.py
standard_names-0.2.7.dist-info/LICENSE
standard_names-0.2.7.dist-info/METADATA
standard_names-0.2.7.dist-info/WHEEL
standard_names-0.2.7.dist-info/entry_points.txt
standard_names-0.2.7.dist-info/top_level.txt
standard_names-0.2.7.dist-info/RECORD
