Metadata-Version: 2.1
Name: standard-names
Version: 0.2.7
Summary: Python utilities for working with CSDMS Standard Names
Author: Eric Hutton
Author-email: eric.hutton@colorado.edu
Maintainer: Eric Hutton, Mark Piper, The CSDMS team
Maintainer-email: eric.hutton@colorado.edu, mark.piper@colorado.edu, csdms@colorado.edu
License: MIT License
Project-URL: Homepage, https://csdms.colorado.edu
Project-URL: Documentation, https://standard-names.readthedocs.io/
Project-URL: Repository, https://github.com/csdms/standard_names
Project-URL: Issues, https://github.com/csdms/standard_names/issues
Keywords: python,utilities,csdms,standard names
Classifier: Development Status :: 4 - Beta
Classifier: Intended Audience :: Science/Research
Classifier: Intended Audience :: Education
Classifier: License :: OSI Approved :: MIT License
Classifier: Operating System :: OS Independent
Classifier: Programming Language :: Python :: 3.9
Classifier: Programming Language :: Python :: 3.10
Classifier: Programming Language :: Python :: 3.11
Classifier: Programming Language :: Python :: 3.12
Classifier: Programming Language :: Python :: 3
Classifier: Topic :: Scientific/Engineering :: Physics
Requires-Python: >=3.9
License-File: LICENSE
Requires-Dist: pyyaml
Requires-Dist: six
Requires-Dist: packaging
Requires-Dist: jinja2
Requires-Dist: py-scripting
Requires-Dist: binaryornot
Provides-Extra: build
Requires-Dist: build ; extra == 'build'
Requires-Dist: twine ; extra == 'build'
Provides-Extra: dev
Requires-Dist: black ; extra == 'dev'
Requires-Dist: isort ; extra == 'dev'
Requires-Dist: flake8 ; extra == 'dev'
Requires-Dist: zest.releaser ; extra == 'dev'
Provides-Extra: docs
Requires-Dist: sphinx ; extra == 'docs'
Provides-Extra: test
Requires-Dist: pytest ; extra == 'test'
Requires-Dist: pytest-cov ; extra == 'test'
Requires-Dist: coverage ; extra == 'test'
